{
    "metadata": {
        "name": "Distributed Sorting System",
        "description": "This system accepts sorting jobs form clients over a webksocket and assigns them to distributed works. It returns the sorted list.",
        "systemVersion": "0.0.1",
        "systemId" : "1234"
    },
    "programs": [
        "simulatedClient/simulatedClient.py",
        "radixSortWorker/radixSortWorker.py",
        "mergeSortWorker/mergeSortWorker.py",
        "bubbleSortWorker/bubbleSortWorker.py",
        "jobHandler/jobHandler.py",
        "utils/start_system.py",
        "utils/stop_system.py"
    ]
}